widehyo_util/__init__.py
widehyo_util/utils.py
widehyo_util-0.0.1.dist-info/METADATA
widehyo_util-0.0.1.dist-info/WHEEL
widehyo_util-0.0.1.dist-info/RECORD
